st_screenwidth_detector/__init__.py
st_screenwidth_detector/frontend/index.html
st_screenwidth_detector/frontend/main.js
st_screenwidth_detector/frontend/package.json
st_screenwidth_detector/frontend/vite.config.js
st_screenwidth_detector/frontend/dist/index.html
st_screenwidth_detector/frontend/dist/assets/index-C5Z8LQe8.js
st_screenwidth_detector-0.1.4.dist-info/METADATA
st_screenwidth_detector-0.1.4.dist-info/WHEEL
st_screenwidth_detector-0.1.4.dist-info/RECORD
