Metadata-Version: 2.4
Name: st-screenwidth-detector
Version: 0.1.4
Summary: Get current screen width when screen size changes
Project-URL: repository, https://github.com/hoishing/st-screenwidth-detector
Author-email: Kelvin Ng <hoishing@gmail.com>
Requires-Python: >=3.12
Requires-Dist: streamlit>=1.44.1
